{
  "id": "villa-farallon",
  "slug": "villa-farallon",
  "title": "Villa Farallon — Punta Aguila 22 — Casa de Campo",
  "region": "La Romana",
  "address": "Punta Aguila 22, Casa de Campo, La Romana, Provincia de La Romana, República Dominicana",
  "coords": { "lat": 18.4271, "lng": -68.9721 },
  "priceUSD": 33563700,
  "sizeM2": 3493,
  "apartmentM2": 3493,
  "parkingM2": 0,
  "storageM2": 0,
  "beds": 13,
  "baths": 16.5,
  "features": [
    "Sea front location",
    "6,894 m² lot",
    "13 guest rooms",
    "3 staff rooms",
    "16 full bathrooms",
    "3 half bathrooms"
  ],
  "amenities": [
    "Private pool",
    "Gym",
    "Spa with sauna",
    "Jacuzzi",
    "Home theater",
    "Discotheque with DJ booth",
    "Piano",
    "Billiards area",
    "Smart home system",
    "Security personnel",
    "4 vehicles included"
  ],
  "images": [
    "images/propertiesrd/3/1.jpg",
    "images/propertiesrd/3/2.jpg",
    "images/propertiesrd/3/3.jpg",
    "images/propertiesrd/3/4.jpg",
    "images/propertiesrd/3/5.jpg",
    "images/propertiesrd/3/6.jpg",
    "images/propertiesrd/3/7.jpg",
    "images/propertiesrd/3/8.jpg",
    "images/propertiesrd/3/9.jpg",
    "images/propertiesrd/3/10.jpg"
  ],
  "featured": true,
  "status": "published",
  "confotur": false,
  "appraisalUrl": "",
  "description": "Dream property facing the sea in Casa de Campo. Built on a 6,894 m² sea-front lot with 3,493 m² of construction. Features include a 4,000 sq ft master suite, spa, gym, home theater, discotheque, and turnkey operation with all furnishings included.",
  "seoTitle": "Villa Farallon — Punta Aguila 22 — Casa de Campo | Cana Law Selection",
  "seoDescription": "13 bed, 16.5 bath luxury sea-front villa in Casa de Campo with 3,493 m² construction on 6,894 m² lot. Turnkey operation. $33,563,700.",
  "createdAt": "2025-01-15T00:00:00.000Z",
  "updatedAt": "2025-01-15T00:00:00.000Z"
} 